README
bungie.py
caching.py
check.py
destiny_bot.py
functions.py
scraper.py
setup.py
strike.py
destiny_bot.egg-info/PKG-INFO
destiny_bot.egg-info/SOURCES.txt
destiny_bot.egg-info/dependency_links.txt
destiny_bot.egg-info/entry_points.txt
destiny_bot.egg-info/requires.txt
destiny_bot.egg-info/top_level.txt
destiny_bot.egg-info/zip-safe
tests/__init__.py
tests/test_bungie_api.py
tests/test_cache.py
tests/test_get_strike_short_name.py
tests/test_scraping.py